subtranslate/__init__.py
subtranslate/__main__.py
subtranslate/cli.py
subtranslate_py-1.0.4.dist-info/licenses/LICENSE.txt
utilities/__init__.py
utilities/util_srt.py
utilities/util_trans.py
utilities/utils.py
subtranslate_py-1.0.4.dist-info/METADATA
subtranslate_py-1.0.4.dist-info/WHEEL
subtranslate_py-1.0.4.dist-info/entry_points.txt
subtranslate_py-1.0.4.dist-info/top_level.txt
subtranslate_py-1.0.4.dist-info/RECORD
