Metadata-Version: 2.4
Name: subtranslate-py
Version: 1.0.4
Summary: A tool for translating subtitle files
Author-email: tboy1337 <tboy1337.unchanged733@aleeas.com>
License-Expression: MIT
Project-URL: Homepage, https://github.com/tboy1337/SubtranSlate
Project-URL: Bug Tracker, https://github.com/tboy1337/SubtranSlate/issues
Classifier: Programming Language :: Python :: 3
Classifier: Operating System :: OS Independent
Requires-Python: >=3.6
License-File: LICENSE.txt
Requires-Dist: pyexecjs
Requires-Dist: srt
Requires-Dist: requests
Requires-Dist: jieba
Dynamic: license-file
